CHANGES.txt
README.txt
bootstrap.py
buildout.cfg
setup.py
src/z3c/__init__.py
src/z3c.menu.egg-info/PKG-INFO
src/z3c.menu.egg-info/SOURCES.txt
src/z3c.menu.egg-info/dependency_links.txt
src/z3c.menu.egg-info/namespace_packages.txt
src/z3c.menu.egg-info/not-zip-safe
src/z3c.menu.egg-info/requires.txt
src/z3c.menu.egg-info/top_level.txt
src/z3c/menu/__init__.py
src/z3c/menu/simple/README.txt
src/z3c/menu/simple/__init__.py
src/z3c/menu/simple/action.pt
src/z3c/menu/simple/action_item.pt
src/z3c/menu/simple/browser_menu_action_item.pt
src/z3c/menu/simple/interfaces.py
src/z3c/menu/simple/menu.py
src/z3c/menu/simple/menu_item.pt
src/z3c/menu/simple/tab.pt
src/z3c/menu/simple/tab_item.pt
src/z3c/menu/simple/tests.py