Metadata-Version: 1.0
Name: z3c.menu
Version: 0.3.0
Summary: DEPRECATED: Collection of Viewlet-based Menus
Home-page: http://pypi.python.org/pypi/z3c.menu
Author: Zope Corporation and Contributors
Author-email: zope-dev@zope.org
License: ZPL 2.1
Keywords: zope3 menu viewlet simple
Platform: UNKNOWN
Classifier: Development Status :: 7 - Inactive
Classifier: Environment :: Web Environment
Classifier: Intended Audience :: Developers
Classifier: License :: OSI Approved :: Zope Public License
Classifier: Programming Language :: Python
Classifier: Natural Language :: English
Classifier: Operating System :: OS Independent
Classifier: Topic :: Internet :: WWW/HTTP
Classifier: Framework :: Zope3
